lotus/__init__.py
lotus/cache.py
lotus/nl_expression.py
lotus/settings.py
lotus/types.py
lotus/utils.py
lotus/web_search.py
lotus/data_connectors/__init__.py
lotus/data_connectors/connectors.py
lotus/dtype_extensions/__init__.py
lotus/dtype_extensions/image.py
lotus/evals/__init__.py
lotus/evals/llm_as_judge.py
lotus/evals/pairwise_judge.py
lotus/file_extractors/__init__.py
lotus/file_extractors/directory_reader.py
lotus/file_extractors/pptx.py
lotus/models/__init__.py
lotus/models/colbertv2_rm.py
lotus/models/cross_encoder_reranker.py
lotus/models/litellm_rm.py
lotus/models/lm.py
lotus/models/reranker.py
lotus/models/rm.py
lotus/models/sentence_transformers_rm.py
lotus/sem_ops/__init__.py
lotus/sem_ops/cascade_utils.py
lotus/sem_ops/load_sem_index.py
lotus/sem_ops/postprocessors.py
lotus/sem_ops/sem_agg.py
lotus/sem_ops/sem_cluster_by.py
lotus/sem_ops/sem_dedup.py
lotus/sem_ops/sem_extract.py
lotus/sem_ops/sem_filter.py
lotus/sem_ops/sem_index.py
lotus/sem_ops/sem_join.py
lotus/sem_ops/sem_map.py
lotus/sem_ops/sem_partition_by.py
lotus/sem_ops/sem_search.py
lotus/sem_ops/sem_sim_join.py
lotus/sem_ops/sem_topk.py
lotus/templates/__init__.py
lotus/templates/task_instructions.py
lotus/vector_store/__init__.py
lotus/vector_store/faiss_vs.py
lotus/vector_store/qdrant_vs.py
lotus/vector_store/vs.py
lotus/vector_store/weaviate_vs.py
lotus_ai-1.1.4.dist-info/licenses/LICENSE
lotus_ai-1.1.4.dist-info/METADATA
lotus_ai-1.1.4.dist-info/WHEEL
lotus_ai-1.1.4.dist-info/top_level.txt
lotus_ai-1.1.4.dist-info/RECORD
