Metadata-Version: 2.4
Name: lotus-ai
Version: 1.1.4
Summary: lotus
Author-email: Liana Patel <lianapat@stanford.edu>, Siddharth Jha <sidjha@berkeley.edu>
License:                                  Apache License
Classifier: Intended Audience :: Science/Research
Classifier: License :: OSI Approved :: MIT License
Classifier: Operating System :: POSIX :: Linux
Classifier: Programming Language :: Python :: 3
Classifier: Programming Language :: Python :: 3.10
Requires-Python: <3.13,>=3.10
License-File: LICENSE
Requires-Dist: backoff<3.0.0,>=2.2.1
Requires-Dist: faiss-cpu<2.0.0,>=1.8.0.post1
Requires-Dist: litellm<2.0.0,>=1.51.0
Requires-Dist: numpy<2.0.0,>=1.25.0
Requires-Dist: pandas<3.0.0,>=2.0.0
Requires-Dist: sentence-transformers<4.0.0,>=3.0.1
Requires-Dist: tiktoken<1.0.0,>=0.7.0
Requires-Dist: tqdm<5.0.0,>=4.66.4
Provides-Extra: docs
Requires-Dist: sphinx; extra == "docs"
Requires-Dist: sphinx_rtd_theme; extra == "docs"
Provides-Extra: xml
Requires-Dist: lxml; extra == "xml"
Provides-Extra: serpapi
Requires-Dist: google-search-results; extra == "serpapi"
Provides-Extra: arxiv
Requires-Dist: arxiv; extra == "arxiv"
Provides-Extra: file-extractor
Requires-Dist: llama-index; extra == "file-extractor"
Requires-Dist: pymupdf; extra == "file-extractor"
Requires-Dist: docx2txt; extra == "file-extractor"
Requires-Dist: python-pptx; extra == "file-extractor"
Requires-Dist: python-magic; extra == "file-extractor"
Provides-Extra: weaviate
Requires-Dist: weaviate-client; extra == "weaviate"
Provides-Extra: qdrant
Requires-Dist: qdrant-client; extra == "qdrant"
Provides-Extra: data-connectors
Requires-Dist: sqlalchemy; extra == "data-connectors"
Requires-Dist: boto3; extra == "data-connectors"
Requires-Dist: io; extra == "data-connectors"
Provides-Extra: web-search
Requires-Dist: requests; extra == "web-search"
Requires-Dist: azure-cognitiveservices-search-websearch; extra == "web-search"
Requires-Dist: tavily-python; extra == "web-search"
Dynamic: license-file
